{
  "EUR/USD": {
    "score": -3,
    "label": "Sell",
    "direction": "bear",
    "raw": {
      "ema200": 1.15573,
      "ema50": 1.15503,
      "rsi": 50.6,
      "macd_line": -0.000729,
      "macd_signal": -0.000716,
      "dmi_plus": 19.4,
      "dmi_minus": 22.3,
      "adx": 13.0,
      "structure": 0,
      "close": 1.15235
    },
    "signals": {
      "EMA200": -1,
      "EMA50": -1,
      "RSI": 1,
      "MACD": -1,
      "DMI": -1,
      "Structure": 0
    },
    "filter_ok": false,
    "updated": "2026-03-27T09:42:50.815987"
  },
  "GBP/USD": {
    "score": -5,
    "label": "Strong Sell",
    "direction": "bear",
    "raw": {
      "ema200": 1.33544,
      "ema50": 1.33495,
      "rsi": 49.0,
      "macd_line": -0.000879,
      "macd_signal": -0.000758,
      "dmi_plus": 14.3,
      "dmi_minus": 26.2,
      "adx": 17.6,
      "structure": 0,
      "close": 1.33126
    },
    "signals": {
      "EMA200": -1,
      "EMA50": -1,
      "RSI": -1,
      "MACD": -1,
      "DMI": -1,
      "Structure": 0
    },
    "filter_ok": false,
    "updated": "2026-03-27T09:42:50.815987"
  },
  "USD/JPY": {
    "score": 1,
    "label": "Neutral",
    "direction": "neutral",
    "raw": {
      "ema200": 159.20799,
      "ema50": 159.49401,
      "rsi": 49.5,
      "macd_line": 0.087955,
      "macd_signal": 0.079563,
      "dmi_plus": 15.2,
      "dmi_minus": 26.6,
      "adx": 30.2,
      "structure": 0,
      "close": 159.81767
    },
    "signals": {
      "EMA200": 1,
      "EMA50": 1,
      "RSI": -1,
      "MACD": 1,
      "DMI": -1,
      "Structure": 0
    },
    "filter_ok": true,
    "updated": "2026-03-27T09:42:50.815987"
  },
  "USD/CHF": {
    "score": 5,
    "label": "Strong Buy",
    "direction": "bull",
    "raw": {
      "ema200": 0.79043,
      "ema50": 0.79335,
      "rsi": 60.0,
      "macd_line": 0.001026,
      "macd_signal": 0.000953,
      "dmi_plus": 22.3,
      "dmi_minus": 16.6,
      "adx": 20.5,
      "structure": 0,
      "close": 0.79679
    },
    "signals": {
      "EMA200": 1,
      "EMA50": 1,
      "RSI": 1,
      "MACD": 1,
      "DMI": 1,
      "Structure": 0
    },
    "filter_ok": true,
    "updated": "2026-03-27T09:42:50.815987"
  },
  "AUD/USD": {
    "score": 1,
    "label": "Neutral",
    "direction": "neutral",
    "raw": {
      "ema200": 0.69821,
      "ema50": 0.69222,
      "rsi": 59.7,
      "macd_line": -0.000828,
      "macd_signal": -0.001107,
      "dmi_plus": 18.3,
      "dmi_minus": 18.1,
      "adx": 33.0,
      "structure": 0,
      "close": 0.68975
    },
    "signals": {
      "EMA200": -1,
      "EMA50": -1,
      "RSI": 1,
      "MACD": 1,
      "DMI": 1,
      "Structure": 0
    },
    "filter_ok": true,
    "updated": "2026-03-27T09:42:50.815987"
  },
  "USD/CAD": {
    "score": 1,
    "label": "Neutral",
    "direction": "neutral",
    "raw": {
      "ema200": 1.37684,
      "ema50": 1.38284,
      "rsi": 43.5,
      "macd_line": 0.00067,
      "macd_signal": 0.000895,
      "dmi_plus": 18.5,
      "dmi_minus": 17.7,
      "adx": 25.0,
      "structure": 0,
      "close": 1.38504
    },
    "signals": {
      "EMA200": 1,
      "EMA50": 1,
      "RSI": -1,
      "MACD": -1,
      "DMI": 1,
      "Structure": 0
    },
    "filter_ok": true,
    "updated": "2026-03-27T09:42:50.815987"
  },
  "NZD/USD": {
    "score": 1,
    "label": "Neutral",
    "direction": "neutral",
    "raw": {
      "ema200": 0.58168,
      "ema50": 0.5786,
      "rsi": 63.4,
      "macd_line": -0.000514,
      "macd_signal": -0.000728,
      "dmi_plus": 18.0,
      "dmi_minus": 11.9,
      "adx": 18.3,
      "structure": 0,
      "close": 0.5772
    },
    "signals": {
      "EMA200": -1,
      "EMA50": -1,
      "RSI": 1,
      "MACD": 1,
      "DMI": 1,
      "Structure": 0
    },
    "filter_ok": false,
    "updated": "2026-03-27T09:42:50.815987"
  },
  "EUR/JPY": {
    "score": -1,
    "label": "Neutral",
    "direction": "neutral",
    "raw": {
      "ema200": 183.99947,
      "ema50": 184.21725,
      "rsi": 50.0,
      "macd_line": -0.014811,
      "macd_signal": -0.02244,
      "dmi_plus": 8.4,
      "dmi_minus": 28.2,
      "adx": 49.1,
      "structure": 0,
      "close": 184.16503
    },
    "signals": {
      "EMA200": 1,
      "EMA50": -1,
      "RSI": -1,
      "MACD": 1,
      "DMI": -1,
      "Structure": 0
    },
    "filter_ok": true,
    "updated": "2026-03-27T09:42:50.815987"
  },
  "GBP/JPY": {
    "score": -3,
    "label": "Sell",
    "direction": "bear",
    "raw": {
      "ema200": 212.60923,
      "ema50": 212.91193,
      "rsi": 47.4,
      "macd_line": -0.02615,
      "macd_signal": -0.016549,
      "dmi_plus": 16.4,
      "dmi_minus": 18.4,
      "adx": 13.8,
      "structure": 0,
      "close": 212.73567
    },
    "signals": {
      "EMA200": 1,
      "EMA50": -1,
      "RSI": -1,
      "MACD": -1,
      "DMI": -1,
      "Structure": 0
    },
    "filter_ok": false,
    "updated": "2026-03-27T09:42:50.815987"
  },
  "XAU/USD": {
    "score": 1,
    "label": "Neutral",
    "direction": "neutral",
    "raw": {
      "ema200": 4541.83834,
      "ema50": 4448.41368,
      "rsi": 67.6,
      "macd_line": -4.1091,
      "macd_signal": -10.774913,
      "dmi_plus": 32.3,
      "dmi_minus": 12.7,
      "adx": 19.7,
      "structure": 0,
      "close": 4430.90075
    },
    "signals": {
      "EMA200": -1,
      "EMA50": -1,
      "RSI": 1,
      "MACD": 1,
      "DMI": 1,
      "Structure": 0
    },
    "filter_ok": false,
    "updated": "2026-03-27T09:42:50.815987"
  }
}