{
  "themes": [
    {
      "theme": "US-Iran peace talks and Strait of Hormuz proposal driving broad risk sentiment and oil volatility",
      "currencies": [
        "USD",
        "CAD",
        "INR",
        "AUD"
      ],
      "direction": "neutral",
      "confidence": "high"
    },
    {
      "theme": "USD broadly weak on Fed leadership uncertainty and US-Iran de-escalation hopes",
      "currencies": [
        "USD",
        "EUR",
        "NZD",
        "AUD"
      ],
      "direction": "bearish",
      "confidence": "high"
    },
    {
      "theme": "Surging oil prices boosting commodity/energy-linked currencies and complicating central bank calculus",
      "currencies": [
        "CAD",
        "AUD",
        "INR"
      ],
      "direction": "bullish",
      "confidence": "medium"
    },
    {
      "theme": "Critical central bank week: BoJ hike signal, Fed caution, ECB/BoE decisions all imminent",
      "currencies": [
        "JPY",
        "USD",
        "EUR",
        "GBP"
      ],
      "direction": "neutral",
      "confidence": "high"
    }
  ],
  "usd_bias": "bearish",
  "risk_sentiment": "risk-on",
  "key_observation": "Oil approaching $100 and gold above $4,700 simultaneously suggests markets are pricing Iran peace hopes into the dollar but NOT into commodities, creating a disconnect that will resolve violently if talks collapse.",
  "watch": "BoJ policy decision this week \u2014 USD/JPY testing 159.20 breakout zone with markets pricing a June hike signal, making JPY the highest-convexity G10 trade.",
  "updated": "2026-04-27T09:02:02Z",
  "headline_count": 25,
  "status": "ok"
}