{
  "rankings": {
    "USD": 100.0,
    "CHF": 71.0,
    "AUD": 65.4,
    "EUR": 57.6,
    "JPY": 57.4,
    "CAD": 33.2,
    "NZD": 32.6,
    "GBP": 0.0
  },
  "confidence": {
    "EUR": 0.67,
    "GBP": 1.0,
    "USD": 1.0,
    "JPY": 0.75,
    "CHF": 0.67,
    "AUD": 0.8,
    "CAD": 0.67,
    "NZD": 1.0
  },
  "breakdown": {
    "EUR": [
      {
        "pair": "EURUSD",
        "score": -214.769,
        "bull": false
      },
      {
        "pair": "EURJPY",
        "score": -0.013,
        "bull": false
      },
      {
        "pair": "EURGBP",
        "score": 324.196,
        "bull": true
      },
      {
        "pair": "EURCHF",
        "score": -107.747,
        "bull": false
      }
    ],
    "GBP": [
      {
        "pair": "GBPUSD",
        "score": -264.452,
        "bull": false
      },
      {
        "pair": "GBPJPY",
        "score": -0.768,
        "bull": false
      },
      {
        "pair": "EURGBP",
        "score": -324.196,
        "bull": false
      },
      {
        "pair": "GBPCHF",
        "score": -313.156,
        "bull": false
      },
      {
        "pair": "GBPAUD",
        "score": -157.881,
        "bull": false
      }
    ],
    "USD": [
      {
        "pair": "EURUSD",
        "score": 214.769,
        "bull": true
      },
      {
        "pair": "GBPUSD",
        "score": 264.452,
        "bull": true
      },
      {
        "pair": "USDJPY",
        "score": 1.573,
        "bull": true
      },
      {
        "pair": "USDCHF",
        "score": 233.608,
        "bull": true
      },
      {
        "pair": "AUDUSD",
        "score": 133.072,
        "bull": true
      },
      {
        "pair": "USDCAD",
        "score": 261.218,
        "bull": true
      },
      {
        "pair": "NZDUSD",
        "score": 262.045,
        "bull": true
      }
    ],
    "JPY": [
      {
        "pair": "USDJPY",
        "score": -1.573,
        "bull": false
      },
      {
        "pair": "EURJPY",
        "score": 0.013,
        "bull": true
      },
      {
        "pair": "GBPJPY",
        "score": 0.768,
        "bull": true
      },
      {
        "pair": "AUDJPY",
        "score": -0.597,
        "bull": false
      },
      {
        "pair": "NZDJPY",
        "score": 0.071,
        "bull": true
      },
      {
        "pair": "CADJPY",
        "score": -0.207,
        "bull": false
      }
    ],
    "CHF": [
      {
        "pair": "USDCHF",
        "score": -233.608,
        "bull": false
      },
      {
        "pair": "EURCHF",
        "score": 107.747,
        "bull": true
      },
      {
        "pair": "GBPCHF",
        "score": 313.156,
        "bull": true
      }
    ],
    "AUD": [
      {
        "pair": "AUDUSD",
        "score": -133.072,
        "bull": false
      },
      {
        "pair": "AUDJPY",
        "score": 0.597,
        "bull": true
      },
      {
        "pair": "AUDNZD",
        "score": 81.975,
        "bull": true
      },
      {
        "pair": "AUDCAD",
        "score": 74.336,
        "bull": true
      },
      {
        "pair": "GBPAUD",
        "score": 157.881,
        "bull": true
      }
    ],
    "CAD": [
      {
        "pair": "USDCAD",
        "score": -261.218,
        "bull": false
      },
      {
        "pair": "CADJPY",
        "score": 0.207,
        "bull": true
      },
      {
        "pair": "AUDCAD",
        "score": -74.336,
        "bull": false
      }
    ],
    "NZD": [
      {
        "pair": "NZDUSD",
        "score": -262.045,
        "bull": false
      },
      {
        "pair": "NZDJPY",
        "score": -0.071,
        "bull": false
      },
      {
        "pair": "AUDNZD",
        "score": -81.975,
        "bull": false
      }
    ]
  },
  "h4_rankings": {
    "USD": 100.0,
    "CHF": 57.2,
    "CAD": 54.6,
    "JPY": 48.1,
    "EUR": 46.7,
    "AUD": 26.4,
    "NZD": 12.6,
    "GBP": 0.0
  },
  "updated": "2026-05-15T04:15:40.198825"
}