{
  "EUR/USD": {
    "score": 2,
    "label": "Neutral",
    "direction": "neutral",
    "raw": {
      "ema200": 1.15839,
      "ema50": 1.15385,
      "rsi": 59.2,
      "macd_line": 0.000728,
      "macd_signal": 0.000935,
      "dmi_plus": 34.8,
      "dmi_minus": 19.9,
      "adx": 40.1,
      "structure": 1,
      "close": 1.15421
    },
    "signals": {
      "EMA200": -1,
      "EMA50": 1,
      "RSI": 1,
      "MACD": -1,
      "DMI": 1,
      "Structure": 1
    },
    "filter_ok": true,
    "levels": {
      "support": [
        {
          "price": 1.15409,
          "pips": 1.2
        },
        {
          "price": 1.15085,
          "pips": 33.6
        },
        {
          "price": 1.14912,
          "pips": 50.9
        }
      ],
      "resistance": [
        {
          "price": 1.15428,
          "pips": 0.7
        },
        {
          "price": 1.15739,
          "pips": 31.8
        },
        {
          "price": 1.15912,
          "pips": 49.1
        }
      ],
      "current_price": 1.15421
    },
    "updated": "2026-04-02T17:08:28.707294"
  },
  "GBP/USD": {
    "score": 0,
    "label": "Neutral",
    "direction": "neutral",
    "raw": {
      "ema200": 1.33461,
      "ema50": 1.32713,
      "rsi": 50.4,
      "macd_line": -0.00072,
      "macd_signal": -0.000627,
      "dmi_plus": 25.4,
      "dmi_minus": 18.4,
      "adx": 30.0,
      "structure": 1,
      "close": 1.32345
    },
    "signals": {
      "EMA200": -1,
      "EMA50": -1,
      "RSI": 1,
      "MACD": -1,
      "DMI": 1,
      "Structure": 1
    },
    "filter_ok": true,
    "levels": {
      "support": [
        {
          "price": 1.32128,
          "pips": 21.7
        },
        {
          "price": 1.31793,
          "pips": 55.2
        },
        {
          "price": 1.31613,
          "pips": 73.2
        }
      ],
      "resistance": [
        {
          "price": 1.32375,
          "pips": 3.0
        },
        {
          "price": 1.32655,
          "pips": 31.0
        },
        {
          "price": 1.3292,
          "pips": 57.5
        }
      ],
      "current_price": 1.32345
    },
    "updated": "2026-04-02T17:08:28.707294"
  },
  "USD/JPY": {
    "score": 2,
    "label": "Neutral",
    "direction": "neutral",
    "raw": {
      "ema200": 158.57842,
      "ema50": 159.3981,
      "rsi": 51.5,
      "macd_line": -0.068334,
      "macd_signal": -0.16526,
      "dmi_plus": 17.3,
      "dmi_minus": 19.8,
      "adx": 32.7,
      "structure": -1,
      "close": 159.57352
    },
    "signals": {
      "EMA200": 1,
      "EMA50": 1,
      "RSI": 1,
      "MACD": 1,
      "DMI": -1,
      "Structure": -1
    },
    "filter_ok": true,
    "levels": {
      "support": [
        {
          "price": 159.56794,
          "pips": 0.6
        },
        {
          "price": 159.332,
          "pips": 24.2
        },
        {
          "price": 158.86823,
          "pips": 70.5
        }
      ],
      "resistance": [
        {
          "price": 159.64837,
          "pips": 7.5
        },
        {
          "price": 159.89661,
          "pips": 32.3
        },
        {
          "price": 160.39895,
          "pips": 82.5
        }
      ],
      "current_price": 159.57352
    },
    "updated": "2026-04-02T17:08:28.707294"
  },
  "USD/CHF": {
    "score": 2,
    "label": "Neutral",
    "direction": "neutral",
    "raw": {
      "ema200": 0.78899,
      "ema50": 0.79634,
      "rsi": 47.6,
      "macd_line": 0.000169,
      "macd_signal": 3.1e-05,
      "dmi_plus": 23.9,
      "dmi_minus": 23.4,
      "adx": 21.8,
      "structure": -1,
      "close": 0.7985
    },
    "signals": {
      "EMA200": 1,
      "EMA50": 1,
      "RSI": -1,
      "MACD": 1,
      "DMI": 1,
      "Structure": -1
    },
    "filter_ok": true,
    "levels": {
      "support": [
        {
          "price": 0.79845,
          "pips": 0.5
        },
        {
          "price": 0.79573,
          "pips": 27.7
        },
        {
          "price": 0.78778,
          "pips": 107.2
        }
      ],
      "resistance": [
        {
          "price": 0.79866,
          "pips": 1.6
        },
        {
          "price": 0.80275,
          "pips": 42.5
        },
        {
          "price": 0.80517,
          "pips": 66.7
        }
      ],
      "current_price": 0.7985
    },
    "updated": "2026-04-02T17:08:28.707294"
  },
  "AUD/USD": {
    "score": 4,
    "label": "Buy",
    "direction": "bull",
    "raw": {
      "ema200": 0.6977,
      "ema50": 0.69085,
      "rsi": 54.9,
      "macd_line": 0.000393,
      "macd_signal": 0.00036,
      "dmi_plus": 22.1,
      "dmi_minus": 19.9,
      "adx": 27.4,
      "structure": 1,
      "close": 0.69112
    },
    "signals": {
      "EMA200": -1,
      "EMA50": 1,
      "RSI": 1,
      "MACD": 1,
      "DMI": 1,
      "Structure": 1
    },
    "filter_ok": true,
    "levels": {
      "support": [
        {
          "price": 0.69102,
          "pips": 1.0
        },
        {
          "price": 0.68836,
          "pips": 27.6
        },
        {
          "price": 0.68649,
          "pips": 46.3
        }
      ],
      "resistance": [
        {
          "price": 0.69136,
          "pips": 2.4
        },
        {
          "price": 0.69591,
          "pips": 47.9
        },
        {
          "price": 0.69831,
          "pips": 71.9
        }
      ],
      "current_price": 0.69112
    },
    "updated": "2026-04-02T17:08:28.707294"
  },
  "USD/CAD": {
    "score": 0,
    "label": "Neutral",
    "direction": "neutral",
    "raw": {
      "ema200": 1.37666,
      "ema50": 1.38761,
      "rsi": 43.6,
      "macd_line": 0.000634,
      "macd_signal": 0.000806,
      "dmi_plus": 20.4,
      "dmi_minus": 17.2,
      "adx": 25.6,
      "structure": -1,
      "close": 1.39134
    },
    "signals": {
      "EMA200": 1,
      "EMA50": 1,
      "RSI": -1,
      "MACD": -1,
      "DMI": 1,
      "Structure": -1
    },
    "filter_ok": true,
    "levels": {
      "support": [
        {
          "price": 1.3913,
          "pips": 0.4
        },
        {
          "price": 1.3902,
          "pips": 11.4
        },
        {
          "price": 1.3852,
          "pips": 61.4
        }
      ],
      "resistance": [
        {
          "price": 1.39193,
          "pips": 5.9
        },
        {
          "price": 1.3941,
          "pips": 27.6
        },
        {
          "price": 1.39569,
          "pips": 43.5
        }
      ],
      "current_price": 1.39134
    },
    "updated": "2026-04-02T17:08:28.707294"
  },
  "NZD/USD": {
    "score": -5,
    "label": "Strong Sell",
    "direction": "bear",
    "raw": {
      "ema200": 0.5829,
      "ema50": 0.57529,
      "rsi": 49.7,
      "macd_line": -0.000695,
      "macd_signal": -0.000581,
      "dmi_plus": 18.2,
      "dmi_minus": 20.4,
      "adx": 16.1,
      "structure": 0,
      "close": 0.57242
    },
    "signals": {
      "EMA200": -1,
      "EMA50": -1,
      "RSI": -1,
      "MACD": -1,
      "DMI": -1,
      "Structure": 0
    },
    "filter_ok": false,
    "levels": {
      "support": [
        {
          "price": 0.5723,
          "pips": 1.2
        },
        {
          "price": 0.5652,
          "pips": 72.2
        },
        {
          "price": 0.5637,
          "pips": 87.2
        }
      ],
      "resistance": [
        {
          "price": 0.5732,
          "pips": 7.8
        },
        {
          "price": 0.5742,
          "pips": 17.8
        },
        {
          "price": 0.575,
          "pips": 25.8
        }
      ],
      "current_price": 0.57242
    },
    "updated": "2026-04-02T17:08:28.707294"
  },
  "EUR/JPY": {
    "score": 6,
    "label": "Strong Buy",
    "direction": "bull",
    "raw": {
      "ema200": 183.67694,
      "ema50": 183.91843,
      "rsi": 76.4,
      "macd_line": 0.037805,
      "macd_signal": -0.041925,
      "dmi_plus": 21.9,
      "dmi_minus": 7.5,
      "adx": 36.5,
      "structure": 1,
      "close": 184.18469
    },
    "signals": {
      "EMA200": 1,
      "EMA50": 1,
      "RSI": 1,
      "MACD": 1,
      "DMI": 1,
      "Structure": 1
    },
    "filter_ok": true,
    "levels": {
      "support": [
        {
          "price": 183.93491,
          "pips": 25.0
        },
        {
          "price": 183.52683,
          "pips": 65.8
        },
        {
          "price": 182.99442,
          "pips": 119.0
        }
      ],
      "resistance": [
        {
          "price": 184.20689,
          "pips": 2.2
        },
        {
          "price": 184.55728,
          "pips": 37.3
        },
        {
          "price": 184.9119,
          "pips": 72.7
        }
      ],
      "current_price": 184.18469
    },
    "updated": "2026-04-02T17:08:28.707294"
  },
  "GBP/JPY": {
    "score": 0,
    "label": "Neutral",
    "direction": "neutral",
    "raw": {
      "ema200": 211.62259,
      "ema50": 211.53975,
      "rsi": 52.4,
      "macd_line": -0.205629,
      "macd_signal": -0.319319,
      "dmi_plus": 19.1,
      "dmi_minus": 21.7,
      "adx": 21.6,
      "structure": 1,
      "close": 211.18144
    },
    "signals": {
      "EMA200": -1,
      "EMA50": -1,
      "RSI": 1,
      "MACD": 1,
      "DMI": -1,
      "Structure": 1
    },
    "filter_ok": true,
    "levels": {
      "support": [
        {
          "price": 211.07326,
          "pips": 10.8
        },
        {
          "price": 210.5923,
          "pips": 58.9
        },
        {
          "price": 209.79798,
          "pips": 138.3
        }
      ],
      "resistance": [
        {
          "price": 211.38479,
          "pips": 20.3
        },
        {
          "price": 211.99103,
          "pips": 81.0
        },
        {
          "price": 212.47067,
          "pips": 128.9
        }
      ],
      "current_price": 211.18144
    },
    "updated": "2026-04-02T17:08:28.707294"
  },
  "XAU/USD": {
    "score": 2,
    "label": "Neutral",
    "direction": "neutral",
    "raw": {
      "ema200": 4760.07073,
      "ema50": 4600.21324,
      "rsi": 57.9,
      "macd_line": 37.533408,
      "macd_signal": 48.087865,
      "dmi_plus": 26.2,
      "dmi_minus": 20.2,
      "adx": 47.7,
      "structure": 1,
      "close": 4664.623
    },
    "signals": {
      "EMA200": -1,
      "EMA50": 1,
      "RSI": 1,
      "MACD": -1,
      "DMI": 1,
      "Structure": 1
    },
    "filter_ok": true,
    "levels": {
      "support": [
        {
          "price": 4654.91557,
          "pips": 9.7
        },
        {
          "price": 4588.36075,
          "pips": 76.3
        },
        {
          "price": 4533.25987,
          "pips": 131.4
        }
      ],
      "resistance": [
        {
          "price": 4686.1434,
          "pips": 21.5
        },
        {
          "price": 4798.53894,
          "pips": 133.9
        },
        {
          "price": 4879.10052,
          "pips": 214.5
        }
      ],
      "current_price": 4664.623
    },
    "updated": "2026-04-02T17:08:28.707294"
  }
}