{
  "EUR/USD": {
    "score": 2,
    "label": "Neutral",
    "direction": "neutral",
    "raw": {
      "close": 1.17227,
      "ema200": 1.16846,
      "ema50": 1.17279,
      "rsi": 90.5,
      "macd_line": -0.00023,
      "macd_signal": -0.000593,
      "dmi_plus": 30.8,
      "dmi_minus": 0.5,
      "adx": 36.4
    },
    "signals": {
      "EMA200": 1,
      "Momentum": -1,
      "RSI": 1,
      "EMA50": -1,
      "DMI": 1,
      "MACD": -1,
      "Structure": -1
    },
    "filter_ok": false,
    "extended": {
      "extended": false,
      "reasons": [],
      "atr_dist": 0.0
    },
    "conflict": false,
    "structure": {
      "direction": "bear",
      "event": "none",
      "strength": 0.17,
      "multiplier": 1.0
    },
    "adx_weight": 1.0,
    "reset_score": 48,
    "updated": "2026-04-26T09:15:57.295989"
  },
  "GBP/USD": {
    "score": 4,
    "label": "Buy",
    "direction": "bull",
    "raw": {
      "close": 1.35322,
      "ema200": 1.34433,
      "ema50": 1.35114,
      "rsi": 95.4,
      "macd_line": 0.00077,
      "macd_signal": 0.00052,
      "dmi_plus": 39.7,
      "dmi_minus": 7.7,
      "adx": 28.3
    },
    "signals": {
      "EMA200": 1,
      "Momentum": 1,
      "RSI": 1,
      "EMA50": 1,
      "DMI": 1,
      "MACD": -1,
      "Structure": 0
    },
    "filter_ok": false,
    "extended": {
      "extended": true,
      "reasons": [
        "Price 7.3x ATR from EMA200",
        "RSI overbought (95)",
        "10 consecutive bars beyond EMA50"
      ],
      "atr_dist": 7.32
    },
    "conflict": false,
    "structure": {
      "direction": "neutral",
      "event": "none",
      "strength": 0.0,
      "multiplier": 1.0
    },
    "adx_weight": 1.0,
    "reset_score": 49,
    "updated": "2026-04-26T09:15:57.295989"
  },
  "USD/JPY": {
    "score": 0,
    "label": "Neutral",
    "direction": "neutral",
    "raw": {
      "close": 159.36435,
      "ema200": 159.04175,
      "ema50": 159.28798,
      "rsi": 11.1,
      "macd_line": 0.016137,
      "macd_signal": 0.048414,
      "dmi_plus": 7.4,
      "dmi_minus": 22.3,
      "adx": 14.0
    },
    "signals": {
      "EMA200": 1,
      "Momentum": 1,
      "RSI": -1,
      "EMA50": 1,
      "DMI": -1,
      "MACD": 1,
      "Structure": 1
    },
    "filter_ok": false,
    "extended": {
      "extended": false,
      "reasons": [],
      "atr_dist": 0.0
    },
    "conflict": false,
    "structure": {
      "direction": "bull",
      "event": "none",
      "strength": 0.39,
      "multiplier": 1.0
    },
    "adx_weight": 0.0,
    "reset_score": 46,
    "updated": "2026-04-26T09:15:57.295989"
  },
  "USD/CHF": {
    "score": -2,
    "label": "Neutral",
    "direction": "neutral",
    "raw": {
      "close": 0.78495,
      "ema200": 0.7866,
      "ema50": 0.78416,
      "rsi": 18.9,
      "macd_line": 0.000492,
      "macd_signal": 0.000713,
      "dmi_plus": 5.8,
      "dmi_minus": 12.2,
      "adx": 28.3
    },
    "signals": {
      "EMA200": -1,
      "Momentum": 1,
      "RSI": -1,
      "EMA50": 1,
      "DMI": -1,
      "MACD": 1,
      "Structure": 1
    },
    "filter_ok": false,
    "extended": {
      "extended": false,
      "reasons": [],
      "atr_dist": 0.0
    },
    "conflict": false,
    "structure": {
      "direction": "bull",
      "event": "none",
      "strength": 0.99,
      "multiplier": 1.0
    },
    "adx_weight": 1.0,
    "reset_score": 49,
    "updated": "2026-04-26T09:15:57.295989"
  },
  "AUD/USD": {
    "score": 4,
    "label": "Buy",
    "direction": "bull",
    "raw": {
      "close": 0.71511,
      "ema200": 0.70788,
      "ema50": 0.71468,
      "rsi": 82.2,
      "macd_line": -1.1e-05,
      "macd_signal": -0.000121,
      "dmi_plus": 13.3,
      "dmi_minus": 6.6,
      "adx": 32.4
    },
    "signals": {
      "EMA200": 1,
      "Momentum": 1,
      "RSI": 1,
      "EMA50": 1,
      "DMI": 1,
      "MACD": -1,
      "Structure": 0
    },
    "filter_ok": false,
    "extended": {
      "extended": true,
      "reasons": [
        "Price 6.9x ATR from EMA200",
        "RSI overbought (82)",
        "10 consecutive bars beyond EMA50"
      ],
      "atr_dist": 6.85
    },
    "conflict": false,
    "structure": {
      "direction": "neutral",
      "event": "none",
      "strength": 0.0,
      "multiplier": 1.0
    },
    "adx_weight": 1.0,
    "reset_score": 47,
    "updated": "2026-04-26T09:15:57.295989"
  },
  "USD/CAD": {
    "score": -2,
    "label": "Neutral",
    "direction": "neutral",
    "raw": {
      "close": 1.36766,
      "ema200": 1.37502,
      "ema50": 1.36897,
      "rsi": 23.8,
      "macd_line": -0.000178,
      "macd_signal": -0.000205,
      "dmi_plus": 12.3,
      "dmi_minus": 21.2,
      "adx": 26.9
    },
    "signals": {
      "EMA200": -1,
      "Momentum": -1,
      "RSI": -1,
      "EMA50": -1,
      "DMI": -1,
      "MACD": 1,
      "Structure": 1
    },
    "filter_ok": false,
    "extended": {
      "extended": false,
      "reasons": [],
      "atr_dist": 0.0
    },
    "conflict": true,
    "structure": {
      "direction": "bull",
      "event": "none",
      "strength": 0.66,
      "multiplier": 1.0
    },
    "adx_weight": 1.0,
    "reset_score": 49,
    "updated": "2026-04-26T09:15:57.295989"
  },
  "NZD/USD": {
    "score": 2,
    "label": "Neutral",
    "direction": "neutral",
    "raw": {
      "close": 0.58802,
      "ema200": 0.58511,
      "ema50": 0.58797,
      "rsi": 95.0,
      "macd_line": -0.000159,
      "macd_signal": -0.00028,
      "dmi_plus": 29.0,
      "dmi_minus": 4.6,
      "adx": 45.9
    },
    "signals": {
      "EMA200": 1,
      "Momentum": 1,
      "RSI": 1,
      "EMA50": 1,
      "DMI": 1,
      "MACD": -1,
      "Structure": -1
    },
    "filter_ok": false,
    "extended": {
      "extended": false,
      "reasons": [],
      "atr_dist": 0.0
    },
    "conflict": true,
    "structure": {
      "direction": "bear",
      "event": "none",
      "strength": 0.28,
      "multiplier": 1.0
    },
    "adx_weight": 1.0,
    "reset_score": 49,
    "updated": "2026-04-26T09:15:57.295989"
  },
  "EUR/JPY": {
    "score": 3,
    "label": "Buy",
    "direction": "bull",
    "raw": {
      "close": 186.82158,
      "ema200": 185.82937,
      "ema50": 186.80952,
      "rsi": 69.3,
      "macd_line": -0.016505,
      "macd_signal": -0.037185,
      "dmi_plus": 17.1,
      "dmi_minus": 7.1,
      "adx": 22.9
    },
    "signals": {
      "EMA200": 1,
      "Momentum": 1,
      "RSI": 1,
      "EMA50": 1,
      "DMI": 1,
      "MACD": 1,
      "Structure": 0
    },
    "filter_ok": false,
    "extended": {
      "extended": true,
      "reasons": [
        "Price 7.0x ATR from EMA200"
      ],
      "atr_dist": 6.97
    },
    "conflict": false,
    "structure": {
      "direction": "neutral",
      "event": "none",
      "strength": 0.0,
      "multiplier": 1.0
    },
    "adx_weight": 0.75,
    "reset_score": 47,
    "updated": "2026-04-26T09:15:57.295989"
  },
  "GBP/JPY": {
    "score": 4,
    "label": "Buy",
    "direction": "bull",
    "raw": {
      "close": 215.65713,
      "ema200": 213.79995,
      "ema50": 215.2183,
      "rsi": 90.4,
      "macd_line": 0.145229,
      "macd_signal": 0.148584,
      "dmi_plus": 21.2,
      "dmi_minus": 8.3,
      "adx": 26.8
    },
    "signals": {
      "EMA200": 1,
      "Momentum": 1,
      "RSI": 1,
      "EMA50": 1,
      "DMI": 1,
      "MACD": -1,
      "Structure": 1
    },
    "filter_ok": false,
    "extended": {
      "extended": true,
      "reasons": [
        "Price 9.6x ATR from EMA200",
        "RSI overbought (90)",
        "10 consecutive bars beyond EMA50"
      ],
      "atr_dist": 9.57
    },
    "conflict": false,
    "structure": {
      "direction": "bull",
      "event": "none",
      "strength": 1.0,
      "multiplier": 1.0
    },
    "adx_weight": 1.0,
    "reset_score": 42,
    "updated": "2026-04-26T09:15:57.295989"
  },
  "AUD/JPY": {
    "score": 4,
    "label": "Buy",
    "direction": "bull",
    "raw": {
      "close": 113.96891,
      "ema200": 112.58103,
      "ema50": 113.83896,
      "rsi": 64.3,
      "macd_line": 0.010407,
      "macd_signal": 0.015527,
      "dmi_plus": 7.2,
      "dmi_minus": 10.8,
      "adx": 46.1
    },
    "signals": {
      "EMA200": 1,
      "Momentum": 1,
      "RSI": 1,
      "EMA50": 1,
      "DMI": -1,
      "MACD": 1,
      "Structure": 0
    },
    "filter_ok": false,
    "extended": {
      "extended": true,
      "reasons": [
        "Price 8.6x ATR from EMA200",
        "10 consecutive bars beyond EMA50"
      ],
      "atr_dist": 8.55
    },
    "conflict": false,
    "structure": {
      "direction": "neutral",
      "event": "none",
      "strength": 0.0,
      "multiplier": 1.0
    },
    "adx_weight": 1.0,
    "reset_score": 45,
    "updated": "2026-04-26T09:15:57.295989"
  },
  "NZD/JPY": {
    "score": 5,
    "label": "Strong Buy",
    "direction": "bull",
    "raw": {
      "close": 93.70773,
      "ema200": 93.05368,
      "ema50": 93.65585,
      "rsi": 87.5,
      "macd_line": -0.015588,
      "macd_signal": -0.01603,
      "dmi_plus": 21.6,
      "dmi_minus": 4.2,
      "adx": 55.4
    },
    "signals": {
      "EMA200": 1,
      "Momentum": 1,
      "RSI": 1,
      "EMA50": 1,
      "DMI": 1,
      "MACD": 1,
      "Structure": 0
    },
    "filter_ok": false,
    "extended": {
      "extended": true,
      "reasons": [
        "Price 8.4x ATR from EMA200",
        "RSI overbought (87)",
        "10 consecutive bars beyond EMA50"
      ],
      "atr_dist": 8.39
    },
    "conflict": false,
    "structure": {
      "direction": "neutral",
      "event": "none",
      "strength": 0.0,
      "multiplier": 1.0
    },
    "adx_weight": 1.0,
    "reset_score": 50,
    "updated": "2026-04-26T09:15:57.295989"
  },
  "CAD/JPY": {
    "score": 2,
    "label": "Neutral",
    "direction": "neutral",
    "raw": {
      "close": 116.52773,
      "ema200": 115.66995,
      "ema50": 116.35818,
      "rsi": 48.3,
      "macd_line": 0.027097,
      "macd_signal": 0.052639,
      "dmi_plus": 7.8,
      "dmi_minus": 8.1,
      "adx": 21.4
    },
    "signals": {
      "EMA200": 1,
      "Momentum": 1,
      "RSI": -1,
      "EMA50": 1,
      "DMI": -1,
      "MACD": 1,
      "Structure": 1
    },
    "filter_ok": false,
    "extended": {
      "extended": false,
      "reasons": [],
      "atr_dist": 0.0
    },
    "conflict": false,
    "structure": {
      "direction": "bull",
      "event": "none",
      "strength": 0.05,
      "multiplier": 1.0
    },
    "adx_weight": 0.75,
    "reset_score": 13,
    "updated": "2026-04-26T09:15:57.295989"
  },
  "_ohlcv": {}
}